LICENSE.txt
MANIFEST.in
README.rst
requirements.txt
setup.cfg
setup.py
zeugma/__init__.py
zeugma/conf.py
zeugma/embeddings.py
zeugma/keras_transformers.py
zeugma/logger.py
zeugma/texttransformers.py
zeugma.egg-info/PKG-INFO
zeugma.egg-info/SOURCES.txt
zeugma.egg-info/dependency_links.txt
zeugma.egg-info/requires.txt
zeugma.egg-info/top_level.txt