Metadata-Version: 1.1
Name: zeugma
Version: 0.39
Summary: Unified framework for word embeddings (Word2Vec, GloVe, FastText, ...) compatible with scikit-learn Pipeline
Home-page: https://github.com/nkthiebaut
Author: Nicolas Thiebaut
Author-email: nkthiebaut@gmail.com
License: MIT
Download-URL: https://github.com/nkthiebaut/zeugma/archive/0.39.tar.gz
Keywords: embeddings
Platform: UNKNOWN
